robotnikmq/__init__.py
robotnikmq/config.py
robotnikmq/core.py
robotnikmq/error.py
robotnikmq/log.py
robotnikmq/rpc_client.py
robotnikmq/rpc_server.py
robotnikmq/subscriber.py
robotnikmq/topic.py
robotnikmq/utils.py
robotnikmq-0.7.7.dist-info/WHEEL
robotnikmq-0.7.7.dist-info/METADATA
robotnikmq-0.7.7.dist-info/licenses/LICENSE
robotnikmq-0.7.7.dist-info/RECORD
