Metadata-Version: 2.1
Name: robotnikmq
Version: 0.7.7
Summary: Utilities for safe, efficient, and scalable infrastructure using RabbitMQ
License: GPL-3.0-or-later
Author-email: Eugene Kovalev <eugene@kovalev.systems>
Requires-Python: >3.9.0,<4.0
Requires-Dist: arrow>=1.2.3
Requires-Dist: funcy>=1.17
Requires-Dist: loguru>=0.7.0
Requires-Dist: pika>=1.3.0
Requires-Dist: pydantic>=1.0
Requires-Dist: pyyaml>=6.0
Requires-Dist: tenacity>=8.2.2
Requires-Dist: typeguard>=4.0.0
Requires-Dist: types-pika>=1.2.0b1
Requires-Dist: types-pyyaml>=6.0.11
Requires-Dist: typing-extensions>=4.5.0
